adc_webkit/__init__.py
adc_webkit/errors.py
adc_webkit/py.typed
adc_webkit/types/__init__.py
adc_webkit/types/file.py
adc_webkit/types/http.py
adc_webkit/web/__init__.py
adc_webkit/web/web.py
adc_webkit/web/auth/__init__.py
adc_webkit/web/auth/base.py
adc_webkit/web/auth/jwt.py
adc_webkit/web/body_parsers/__init__.py
adc_webkit/web/body_parsers/base.py
adc_webkit/web/body_parsers/factory.py
adc_webkit/web/body_parsers/form_data.py
adc_webkit/web/body_parsers/json.py
adc_webkit/web/body_parsers/stream.py
adc_webkit/web/endpoints/__init__.py
adc_webkit/web/endpoints/base.py
adc_webkit/web/endpoints/json.py
adc_webkit/web/endpoints/request_context.py
adc_webkit/web/endpoints/response.py
adc_webkit/web/endpoints/stream.py
adc_webkit/web/openapi/__init__.py
adc_webkit/web/openapi/auth.py
adc_webkit/web/openapi/endpoint.py
adc_webkit/web/openapi/schema.py
adc_webkit-0.1.0.dist-info/licenses/LICENSE
adc_webkit-0.1.0.dist-info/METADATA
adc_webkit-0.1.0.dist-info/WHEEL
adc_webkit-0.1.0.dist-info/top_level.txt
adc_webkit-0.1.0.dist-info/RECORD
